hardware/memory-behavior.v
// Simulation-only persistent memory abstraction. No analog physics or synthesis claim.
module memory_behavior(input clk, commit, write, fault,
 input [3:0] addr, input [7:0] wdata, output [7:0] rdata);
 reg [7:0] words [0:15];
 integer i;
 initial for(i=0;i<16;i=i+1) words[i]=0;
 assign rdata=words[addr];
 always @(posedge clk) if(commit && write && !fault) words[addr]<=wdata;
endmodule

hardware/controller-synth.v
/* Generated by Yosys 0.33 (git sha1 2584903a060) */

module controller(clk, reset, req_valid, req_write, req_addr, req_wdata, req_ready, rsp_valid, rsp_error, rsp_rdata, mem_commit, mem_write, mem_addr, mem_wdata, mem_rdata, mem_fault);
  wire _000_;
  wire _001_;
  wire _002_;
  wire _003_;
  wire _004_;
  wire _005_;
  wire _006_;
  wire _007_;
  wire _008_;
  wire _009_;
  wire _010_;
  wire _011_;
  wire _012_;
  wire _013_;
  wire _014_;
  wire _015_;
  wire _016_;
  wire _017_;
  wire _018_;
  wire _019_;
  wire _020_;
  wire _021_;
  wire _022_;
  wire _023_;
  wire _024_;
  wire _025_;
  wire _026_;
  wire _027_;
  wire _028_;
  wire _029_;
  wire _030_;
  wire _031_;
  wire _032_;
  wire _033_;
  wire _034_;
  wire _035_;
  wire _036_;
  wire _037_;
  wire _038_;
  wire _039_;
  wire _040_;
  wire _041_;
  wire _042_;
  wire _043_;
  wire _044_;
  wire _045_;
  wire _046_;
  wire _047_;
  wire _048_;
  wire _049_;
  wire _050_;
  wire _051_;
  wire _052_;
  wire _053_;
  reg [3:0] addr_latched;
  reg busy;
  input clk;
  wire clk;
  reg [7:0] data_latched;
  output [3:0] mem_addr;
  wire [3:0] mem_addr;
  output mem_commit;
  wire mem_commit;
  input mem_fault;
  wire mem_fault;
  input [7:0] mem_rdata;
  wire [7:0] mem_rdata;
  output [7:0] mem_wdata;
  wire [7:0] mem_wdata;
  output mem_write;
  wire mem_write;
  reg [7:0] remaining;
  input [3:0] req_addr;
  wire [3:0] req_addr;
  output req_ready;
  wire req_ready;
  input req_valid;
  wire req_valid;
  input [7:0] req_wdata;
  wire [7:0] req_wdata;
  input req_write;
  wire req_write;
  input reset;
  wire reset;
  output rsp_error;
  reg rsp_error;
  output [7:0] rsp_rdata;
  reg [7:0] rsp_rdata;
  output rsp_valid;
  reg rsp_valid;
  reg write_latched;
  assign req_ready = ~(reset | busy);
  assign _004_ = req_ready & req_valid;
  assign _000_ = _004_ | busy;
  assign _002_ = reset | ~(busy);
  assign _008_ = remaining[1] | ~(remaining[0]);
  assign _009_ = ~(remaining[3] | remaining[2]);
  assign _010_ = _009_ & ~(_008_);
  assign _011_ = ~(remaining[5] | remaining[4]);
  assign _012_ = remaining[7] | remaining[6];
  assign _013_ = _012_ | ~(_011_);
  assign _003_ = _010_ & ~(_013_);
  assign _014_ = ~_004_;
  assign _015_ = ~(_003_ & busy);
  assign _001_ = _014_ & ~(_015_);
  assign mem_commit = ~(_015_ | reset);
  assign _046_ = mem_rdata[0] & ~(mem_fault);
  assign _047_ = mem_rdata[1] & ~(mem_fault);
  assign _048_ = mem_rdata[2] & ~(mem_fault);
  assign _049_ = mem_rdata[3] & ~(mem_fault);
  assign _050_ = mem_rdata[4] & ~(mem_fault);
  assign _051_ = mem_rdata[5] & ~(mem_fault);
  assign _052_ = mem_rdata[6] & ~(mem_fault);
  assign _053_ = mem_rdata[7] & ~(mem_fault);
  assign _016_ = _003_ | remaining[0];
  assign _037_ = _014_ & ~(_016_);
  assign _017_ = ~req_write;
  assign _018_ = ~(remaining[1] ^ remaining[0]);
  assign _038_ = _004_ ? _017_ : _018_;
  assign _019_ = ~(remaining[1] | remaining[0]);
  assign _020_ = ~(_019_ ^ remaining[2]);
  assign _021_ = ~(_020_ | _003_);
  assign _039_ = _004_ ? req_write : _021_;
  assign _022_ = _019_ & ~(remaining[2]);
  assign _023_ = ~(_022_ ^ remaining[3]);
  assign _024_ = _023_ | _003_;
  assign _040_ = _014_ & ~(_024_);
  assign _025_ = _009_ & ~(_019_);
  assign _026_ = _009_ & ~(_025_);
  assign _027_ = ~(_026_ ^ remaining[4]);
  assign _028_ = _027_ | _003_;
  assign _041_ = _014_ & ~(_028_);
  assign _029_ = _026_ & ~(remaining[4]);
  assign _030_ = ~(_029_ ^ remaining[5]);
  assign _031_ = _030_ | _003_;
  assign _042_ = _014_ & ~(_031_);
  assign _032_ = _011_ & ~(_026_);
  assign _033_ = _032_ | ~(_011_);
  assign _034_ = _033_ ^ remaining[6];
  assign _035_ = _034_ | _003_;
  assign _043_ = _014_ & ~(_035_);
  assign _036_ = _033_ | remaining[6];
  assign _005_ = _036_ ^ remaining[7];
  assign _006_ = _005_ | _003_;
  assign _044_ = _014_ & ~(_006_);
  assign _007_ = busy & ~(_003_);
  assign _045_ = _007_ | ~(_014_);
  always @(posedge clk)
    if (reset) busy <= 1'h0;
    else busy <= _045_;
  always @(posedge clk)
    if (reset) rsp_error <= 1'h0;
    else if (_001_) rsp_error <= mem_fault;
  always @(posedge clk)
    if (reset) rsp_rdata[0] <= 1'h0;
    else if (_001_) rsp_rdata[0] <= _046_;
  always @(posedge clk)
    if (reset) rsp_rdata[1] <= 1'h0;
    else if (_001_) rsp_rdata[1] <= _047_;
  always @(posedge clk)
    if (reset) rsp_rdata[2] <= 1'h0;
    else if (_001_) rsp_rdata[2] <= _048_;
  always @(posedge clk)
    if (reset) rsp_rdata[3] <= 1'h0;
    else if (_001_) rsp_rdata[3] <= _049_;
  always @(posedge clk)
    if (reset) rsp_rdata[4] <= 1'h0;
    else if (_001_) rsp_rdata[4] <= _050_;
  always @(posedge clk)
    if (reset) rsp_rdata[5] <= 1'h0;
    else if (_001_) rsp_rdata[5] <= _051_;
  always @(posedge clk)
    if (reset) rsp_rdata[6] <= 1'h0;
    else if (_001_) rsp_rdata[6] <= _052_;
  always @(posedge clk)
    if (reset) rsp_rdata[7] <= 1'h0;
    else if (_001_) rsp_rdata[7] <= _053_;
  always @(posedge clk)
    if (_002_) rsp_valid <= 1'h0;
    else rsp_valid <= _003_;
  always @(posedge clk)
    if (reset) write_latched <= 1'h0;
    else if (_004_) write_latched <= req_write;
  always @(posedge clk)
    if (reset) addr_latched[0] <= 1'h0;
    else if (_004_) addr_latched[0] <= req_addr[0];
  always @(posedge clk)
    if (reset) addr_latched[1] <= 1'h0;
    else if (_004_) addr_latched[1] <= req_addr[1];
  always @(posedge clk)
    if (reset) addr_latched[2] <= 1'h0;
    else if (_004_) addr_latched[2] <= req_addr[2];
  always @(posedge clk)
    if (reset) addr_latched[3] <= 1'h0;
    else if (_004_) addr_latched[3] <= req_addr[3];
  always @(posedge clk)
    if (reset) data_latched[0] <= 1'h0;
    else if (_004_) data_latched[0] <= req_wdata[0];
  always @(posedge clk)
    if (reset) data_latched[1] <= 1'h0;
    else if (_004_) data_latched[1] <= req_wdata[1];
  always @(posedge clk)
    if (reset) data_latched[2] <= 1'h0;
    else if (_004_) data_latched[2] <= req_wdata[2];
  always @(posedge clk)
    if (reset) data_latched[3] <= 1'h0;
    else if (_004_) data_latched[3] <= req_wdata[3];
  always @(posedge clk)
    if (reset) data_latched[4] <= 1'h0;
    else if (_004_) data_latched[4] <= req_wdata[4];
  always @(posedge clk)
    if (reset) data_latched[5] <= 1'h0;
    else if (_004_) data_latched[5] <= req_wdata[5];
  always @(posedge clk)
    if (reset) data_latched[6] <= 1'h0;
    else if (_004_) data_latched[6] <= req_wdata[6];
  always @(posedge clk)
    if (reset) data_latched[7] <= 1'h0;
    else if (_004_) data_latched[7] <= req_wdata[7];
  always @(posedge clk)
    if (reset) remaining[0] <= 1'h0;
    else if (_000_) remaining[0] <= _037_;
  always @(posedge clk)
    if (reset) remaining[1] <= 1'h0;
    else if (_000_) remaining[1] <= _038_;
  always @(posedge clk)
    if (reset) remaining[2] <= 1'h0;
    else if (_000_) remaining[2] <= _039_;
  always @(posedge clk)
    if (reset) remaining[3] <= 1'h0;
    else if (_000_) remaining[3] <= _040_;
  always @(posedge clk)
    if (reset) remaining[4] <= 1'h0;
    else if (_000_) remaining[4] <= _041_;
  always @(posedge clk)
    if (reset) remaining[5] <= 1'h0;
    else if (_000_) remaining[5] <= _042_;
  always @(posedge clk)
    if (reset) remaining[6] <= 1'h0;
    else if (_000_) remaining[6] <= _043_;
  always @(posedge clk)
    if (reset) remaining[7] <= 1'h0;
    else if (_000_) remaining[7] <= _044_;
  assign mem_addr = addr_latched;
  assign mem_wdata = data_latched;
  assign mem_write = write_latched;
endmodule

hardware/tb.v
`timescale 1ns/1ps
module tb;
 reg clk=0,reset=1,req_valid=0,req_write=0,fault=0;
 reg [3:0] req_addr=0;reg [7:0] req_wdata=0;
 wire ready,rsp_valid,rsp_error,commit,mem_write;
 wire [7:0] rsp_rdata,mem_wdata,mem_rdata;wire [3:0] mem_addr;
 integer count=0;
 always #5 clk=~clk;
 controller dut(clk,reset,req_valid,req_write,req_addr,req_wdata,ready,
  rsp_valid,rsp_error,rsp_rdata,commit,mem_write,mem_addr,mem_wdata,mem_rdata,fault);
 memory_behavior memory(clk,commit,mem_write,fault,mem_addr,mem_wdata,mem_rdata);
 task transact;
  input wr;input [3:0] addr;input [7:0] data;input bad;
  input [7:0] expected;
  integer cycles;
  begin
   @(negedge clk);if(!ready)$fatal(1,"not ready at request");
   req_valid=1;req_write=wr;req_addr=addr;req_wdata=data;fault=bad;
   @(posedge clk);#1;
   if(ready)$fatal(1,"must deassert ready after acceptance");
   @(negedge clk);req_valid=0;cycles=0;
   while(!rsp_valid)begin @(posedge clk);#1;cycles=cycles+1;end
   if(cycles!=(wr?4:2))$fatal(1,"wrong response latency: %0d",cycles);
   if(rsp_error!==bad)$fatal(1,"error propagation failed");
   if(!wr && rsp_rdata!==expected)$fatal(1,"read mismatch");
   if(!ready)$fatal(1,"did not return ready");
   count=count+1;fault=0;
  end
 endtask
 initial begin
  $dumpfile("controller.vcd");$dumpvars(0,tb);
  repeat(2)@(negedge clk);reset=0;
  transact(0,0,0,0,0);
  transact(1,0,8'ha5,0,0);transact(0,0,0,0,8'ha5);
  transact(1,15,8'h3c,0,0);transact(0,15,0,0,8'h3c);
  transact(1,15,8'hff,1,0);transact(0,15,0,0,8'h3c);
  transact(0,15,0,1,0);
  // A pulse while busy is not accepted; accepted command pins are latched.
  @(negedge clk);req_valid=1;req_write=1;req_addr=2;req_wdata=8'h55;
  @(negedge clk);req_addr=3;req_wdata=8'haa;
  @(negedge clk);req_valid=0;
  wait(rsp_valid);@(negedge clk);
  transact(0,2,0,0,8'h55);transact(0,3,0,0,0);
  // Reset aborts an in-flight write; committed nonvolatile state survives controller reset.
  @(negedge clk);req_valid=1;req_write=1;req_addr=0;req_wdata=8'h77;
  @(negedge clk);req_valid=0;reset=1;
  @(negedge clk);reset=0;
  transact(0,0,0,0,8'ha5);
  $display("PASS: %0d checked transactions; latency, endpoints, fault, busy, reset-abort, persistence",count);
  $finish;
 end
 initial begin #5000;$fatal(1,"test timeout");end
endmodule

hardware/controller.vcd
$date
	Sat Sep 26 13:33:37 2026
$end
$version
	Icarus Verilog
$end
$timescale
	1ps
$end
$scope module tb $end
$var wire 1 ! rsp_valid $end
$var wire 8 " rsp_rdata [7:0] $end
$var wire 1 # rsp_error $end
$var wire 1 $ ready $end
$var wire 1 % mem_write $end
$var wire 8 & mem_wdata [7:0] $end
$var wire 8 ' mem_rdata [7:0] $end
$var wire 4 ( mem_addr [3:0] $end
$var wire 1 ) commit $end
$var reg 1 * clk $end
$var reg 1 + fault $end
$var reg 4 , req_addr [3:0] $end
$var reg 1 - req_valid $end
$var reg 8 . req_wdata [7:0] $end
$var reg 1 / req_write $end
$var reg 1 0 reset $end
$var integer 32 1 count [31:0] $end
$scope module dut $end
$var wire 1 2 _000_ $end
$var wire 1 3 _001_ $end
$var wire 1 4 _002_ $end
$var wire 1 5 _003_ $end
$var wire 1 6 _004_ $end
$var wire 1 7 _005_ $end
$var wire 1 8 _006_ $end
$var wire 1 9 _007_ $end
$var wire 1 : _008_ $end
$var wire 1 ; _009_ $end
$var wire 1 < _010_ $end
$var wire 1 = _011_ $end
$var wire 1 > _012_ $end
$var wire 1 ? _013_ $end
$var wire 1 @ _014_ $end
$var wire 1 A _015_ $end
$var wire 1 B _016_ $end
$var wire 1 C _017_ $end
$var wire 1 D _018_ $end
$var wire 1 E _019_ $end
$var wire 1 F _020_ $end
$var wire 1 G _021_ $end
$var wire 1 H _022_ $end
$var wire 1 I _023_ $end
$var wire 1 J _024_ $end
$var wire 1 K _025_ $end
$var wire 1 L _026_ $end
$var wire 1 M _027_ $end
$var wire 1 N _028_ $end
$var wire 1 O _029_ $end
$var wire 1 P _030_ $end
$var wire 1 Q _031_ $end
$var wire 1 R _032_ $end
$var wire 1 S _033_ $end
$var wire 1 T _034_ $end
$var wire 1 U _035_ $end
$var wire 1 V _036_ $end
$var wire 1 W _037_ $end
$var wire 1 X _040_ $end
$var wire 1 Y _041_ $end
$var wire 1 Z _042_ $end
$var wire 1 [ _043_ $end
$var wire 1 \ _044_ $end
$var wire 1 ] _045_ $end
$var wire 1 ^ _046_ $end
$var wire 1 _ _047_ $end
$var wire 1 ` _048_ $end
$var wire 1 a _049_ $end
$var wire 1 b _050_ $end
$var wire 1 c _051_ $end
$var wire 1 d _052_ $end
$var wire 1 e _053_ $end
$var wire 1 * clk $end
$var wire 4 f mem_addr [3:0] $end
$var wire 1 ) mem_commit $end
$var wire 1 + mem_fault $end
$var wire 8 g mem_wdata [7:0] $end
$var wire 1 % mem_write $end
$var wire 4 h req_addr [3:0] $end
$var wire 1 $ req_ready $end
$var wire 1 - req_valid $end
$var wire 8 i req_wdata [7:0] $end
$var wire 1 / req_write $end
$var wire 1 0 reset $end
$var wire 8 j mem_rdata [7:0] $end
$var wire 1 k _039_ $end
$var wire 1 l _038_ $end
$var reg 4 m addr_latched [3:0] $end
$var reg 1 n busy $end
$var reg 8 o data_latched [7:0] $end
$var reg 8 p remaining [7:0] $end
$var reg 1 # rsp_error $end
$var reg 8 q rsp_rdata [7:0] $end
$var reg 1 ! rsp_valid $end
$var reg 1 r write_latched $end
$upscope $end
$scope module memory $end
$var wire 4 s addr [3:0] $end
$var wire 1 * clk $end
$var wire 1 ) commit $end
$var wire 1 + fault $end
$var wire 8 t rdata [7:0] $end
$var wire 8 u wdata [7:0] $end
$var wire 1 % write $end
$var integer 32 v i [31:0] $end
$upscope $end
$scope task transact $end
$var reg 4 w addr [3:0] $end
$var reg 1 x bad $end
$var reg 8 y data [7:0] $end
$var reg 8 z expected [7:0] $end
$var reg 1 { wr $end
$var integer 32 | cycles [31:0] $end
$upscope $end
$upscope $end
$enddefinitions $end
$comment Show the parameter values. $end
$dumpall
$end
#0
$dumpvars
bx |
x{
bx z
bx y
xx
bx w
b10000 v
bx u
bx t
bx s
xr
bx q
bx p
bx o
xn
bx m
xl
xk
bx j
b0 i
b0 h
bx g
bx f
xe
xd
xc
xb
xa
x`
x_
x^
x]
x\
x[
xZ
xY
xX
xW
xV
xU
xT
xS
xR
xQ
xP
xO
xN
xM
xL
xK
xJ
xI
xH
xG
xF
xE
xD
1C
xB
xA
1@
x?
x>
x=
x<
x;
x:
x9
x8
x7
06
x5
14
x3
x2
b0 1
10
0/
b0 .
0-
b0 ,
0+
0*
0)
bx (
bx '
bx &
x%
0$
x#
bx "
x!
$end
#5000
1\
1[
1Z
08
1Y
0U
07
0Q
0T
0V
0N
0P
0S
1W
1k
1X
0M
0R
1G
1O
0B
0J
1L
05
0I
0<
0F
0K
0?
03
1l
1H
1:
1D
1E
1;
1=
0]
1A
0e
0d
0c
0b
0a
0`
0_
0^
0>
09
02
0n
0#
b0 "
b0 q
0!
0%
0r
b0 '
b0 j
b0 t
b0 (
b0 f
b0 m
b0 s
b0 &
b0 g
b0 u
b0 o
b0 p
1*
#10000
0*
#15000
1*
#20000
1$
b0 z
0x
b0 y
b0 w
0{
00
0*
#25000
1*
#30000
1]
0W
0X
0Y
0Z
0[
0\
12
0@
0k
16
1-
0*
#35000
18
1U
17
1Q
1T
1V
1N
1P
1S
1M
1R
0O
0G
1J
0L
1I
1F
1K
1W
0X
0Y
0Z
0[
0\
0H
1@
0l
0k
0D
0E
06
04
0$
19
b10 p
1n
1*
#40000
b0 |
0-
0*
#45000
13
1)
0]
0A
09
15
1<
0W
0:
1B
b1 p
1*
#46000
b1 |
#50000
0*
#55000
1\
1[
1Z
08
1Y
0U
07
0Q
0T
0V
0N
0P
0S
1W
1k
1X
0M
0R
1G
1O
0B
0J
1L
05
0I
0<
0F
0K
1l
1H
03
0)
1:
1D
1E
1A
14
1$
02
b0 p
1!
0n
1*
#56000
b10100101 y
1{
b1 1
b10 |
#60000
1]
0W
0X
0Y
0Z
0[
0\
12
0@
0l
0C
16
b10100101 .
b10100101 i
1/
1-
0*
#65000
18
1U
17
1Q
1T
1V
1N
1P
1S
1M
1R
0k
1J
1W
0X
0Y
0Z
0[
0\
0O
0G
1I
1@
1l
0L
06
0;
1F
0H
04
0$
19
1n
0!
1%
1r
b10100101 &
b10100101 g
b10100101 u
b10100101 o
b100 p
1*
#70000
b0 |
0-
0*
#75000
0\
0[
0Z
18
0Y
1U
17
1Q
1T
1V
1N
1P
1S
1M
1R
0k
0O
0G
1K
0L
0W
1;
1F
0E
1B
b11 p
1*
#76000
b1 |
#80000
0*
#85000
1W
0l
0D
0B
b10 p
1*
#86000
b10 |
#90000
0*
#95000
13
1)
0]
0A
09
15
1<
0W
0:
1B
b1 p
1*
#96000
b11 |
#100000
0*
#105000
1\
1[
1Z
08
1Y
0U
07
0Q
0T
0V
0N
0P
0S
1W
1k
1X
0M
0R
1G
1O
0B
0J
1L
05
0I
0<
0F
0K
03
0)
1l
1H
1:
1D
1E
1A
14
1$
1e
1c
1`
1^
02
0n
1!
b0 p
b10100101 '
b10100101 j
b10100101 t
1*
#106000
b10100101 z
b0 y
0{
b10 1
b100 |
#110000
1]
0W
0X
0Y
0Z
0[
0\
12
0@
0k
1C
16
b0 .
b0 i
0/
1-
0*
#115000
18
1U
17
1Q
1T
1V
1N
1P
1S
1M
1R
0O
0G
1J
0L
1I
1F
1K
1W
0X
0Y
0Z
0[
0\
0H
1@
0l
0k
0D
0E
06
04
0$
19
b10 p
b0 &
b0 g
b0 u
b0 o
0%
0r
0!
1n
1*
#120000
b0 |
0-
0*
#125000
13
1)
0]
0A
09
15
1<
0W
0:
1B
b1 p
1*
#126000
b1 |
#130000
0*
#135000
1\
1[
1Z
08
1Y
0U
07
0Q
0T
0V
0N
0P
0S
1W
1k
1X
0M
0R
1G
1O
0B
0J
1L
05
0I
0<
0F
0K
1l
1H
03
0)
1:
1D
1E
1A
14
1$
02
b0 p
1!
b10100101 "
b10100101 q
0n
1*
#136000
b0 z
b111100 y
b1111 w
1{
b11 1
b10 |
#140000
1]
0W
0X
0Y
0Z
0[
0\
12
0@
0l
0C
16
b111100 .
b111100 i
b1111 ,
b1111 h
1/
1-
0*
#145000
18
1U
17
1Q
1T
1V
1N
1P
1S
1M
1R
0k
1J
1W
0X
0Y
0Z
0[
0\
0O
0G
1I
1@
1l
0L
06
0;
1F
0H
04
0$
0e
0c
0`
0^
19
1n
0!
1%
1r
b0 '
b0 j
b0 t
b1111 (
b1111 f
b1111 m
b1111 s
b111100 &
b111100 g
b111100 u
b111100 o
b100 p
1*
#150000
b0 |
0-
0*
#155000
0\
0[
0Z
18
0Y
1U
17
1Q
1T
1V
1N
1P
1S
1M
1R
0k
0O
0G
1K
0L
0W
1;
1F
0E
1B
b11 p
1*
#156000
b1 |
#160000
0*
#165000
1W
0l
0D
0B
b10 p
1*
#166000
b10 |
#170000
0*
#175000
13
1)
0]
0A
09
15
1<
0W
0:
1B
b1 p
1*
#176000
b11 |
#180000
0*
#185000
1\
1[
1Z
08
1Y
0U
07
0Q
0T
0V
0N
0P
0S
1W
1k
1X
0M
0R
1G
1O
0B
0J
1L
05
0I
0<
0F
0K
03
0)
1l
1H
1:
1D
1E
1A
14
1$
1c
1b
1a
1`
02
0n
b0 "
b0 q
1!
b0 p
b111100 '
b111100 j
b111100 t
1*
#186000
b111100 z
b0 y
0{
b100 1
b100 |
#190000
1]
0W
0X
0Y
0Z
0[
0\
12
0@
0k
1C
16
b0 .
b0 i
0/
1-
0*
#195000
18
1U
17
1Q
1T
1V
1N
1P
1S
1M
1R
0O
0G
1J
0L
1I
1F
1K
1W
0X
0Y
0Z
0[
0\
0H
1@
0l
0k
0D
0E
06
04
0$
19
b10 p
b0 &
b0 g
b0 u
b0 o
0%
0r
0!
1n
1*
#200000
b0 |
0-
0*
#205000
13
1)
0]
0A
09
15
1<
0W
0:
1B
b1 p
1*
#206000
b1 |
#210000
0*
#215000
1\
1[
1Z
08
1Y
0U
07
0Q
0T
0V
0N
0P
0S
1W
1k
1X
0M
0R
1G
1O
0B
0J
1L
05
0I
0<
0F
0K
1l
1H
03
0)
1:
1D
1E
1A
14
1$
02
b0 p
1!
b111100 "
b111100 q
0n
1*
#216000
b0 z
1x
b11111111 y
1{
b101 1
b10 |
#220000
1]
0W
0X
0Y
0Z
0[
0\
0`
0a
0b
0c
12
0@
0l
0C
16
1+
b11111111 .
b11111111 i
1/
1-
0*
#225000
18
1U
17
1Q
1T
1V
1N
1P
1S
1M
1R
0k
1J
1W
0X
0Y
0Z
0[
0\
0O
0G
1I
1@
1l
0L
06
0;
1F
0H
04
0$
19
1n
0!
1%
1r
b11111111 &
b11111111 g
b11111111 u
b11111111 o
b100 p
1*
#230000
b0 |
0-
0*
#235000
0\
0[
0Z
18
0Y
1U
17
1Q
1T
1V
1N
1P
1S
1M
1R
0k
0O
0G
1K
0L
0W
1;
1F
0E
1B
b11 p
1*
#236000
b1 |
#240000
0*
#245000
1W
0l
0D
0B
b10 p
1*
#246000
b10 |
#250000
0*
#255000
13
1)
0]
0A
09
15
1<
0W
0:
1B
b1 p
1*
#256000
b11 |
#260000
0*
#265000
1\
1[
1Z
08
1Y
0U
07
0Q
0T
0V
0N
0P
0S
1W
1k
1X
0M
0R
1G
1O
0B
0J
1L
05
0I
0<
0F
0K
03
0)
1l
1H
1:
1D
1E
1A
14
1$
02
0n
1#
b0 "
b0 q
1!
b0 p
1*
#266000
1`
1a
1b
1c
b111100 z
0x
b0 y
0{
0+
b110 1
b100 |
#270000
1]
0W
0X
0Y
0Z
0[
0\
12
0@
0k
1C
16
b0 .
b0 i
0/
1-
0*
#275000
18
1U
17
1Q
1T
1V
1N
1P
1S
1M
1R
0O
0G
1J
0L
1I
1F
1K
1W
0X
0Y
0Z
0[
0\
0H
1@
0l
0k
0D
0E
06
04
0$
19
b10 p
b0 &
b0 g
b0 u
b0 o
0%
0r
0!
1n
1*
#280000
b0 |
0-
0*
#285000
13
1)
0]
0A
09
15
1<
0W
0:
1B
b1 p
1*
#286000
b1 |
#290000
0*
#295000
1\
1[
1Z
08
1Y
0U
07
0Q
0T
0V
0N
0P
0S
1W
1k
1X
0M
0R
1G
1O
0B
0J
1L
05
0I
0<
0F
0K
1l
1H
03
0)
1:
1D
1E
1A
14
1$
02
b0 p
1!
b111100 "
b111100 q
0#
0n
1*
#296000
b0 z
1x
b111 1
b10 |
#300000
1]
0W
0X
0Y
0Z
0[
0\
0`
0a
0b
0c
12
0@
0k
16
1+
1-
0*
#305000
18
1U
17
1Q
1T
1V
1N
1P
1S
1M
1R
0O
0G
1J
0L
1I
1W
0X
0Y
0Z
0[
0\
1F
1K
1@
0l
0k
0H
06
0D
0E
04
0$
19
1n
0!
b10 p
1*
#310000
b0 |
0-
0*
#315000
13
1)
0]
0A
09
15
1<
0W
0:
1B
b1 p
1*
#316000
b1 |
#320000
0*
#325000
1\
1[
1Z
08
1Y
0U
07
0Q
0T
0V
0N
0P
0S
1W
1k
1X
0M
0R
1G
1O
0B
0J
1L
05
0I
0<
0F
0K
03
0)
1l
1H
1:
1D
1E
1A
14
1$
02
0n
1#
b0 "
b0 q
1!
b0 p
1*
#326000
1`
1a
1b
1c
0+
b1000 1
b10 |
#330000
1]
0W
0X
0Y
0Z
0[
0\
12
0@
0l
0C
16
b1010101 .
b1010101 i
b10 ,
b10 h
1/
1-
0*
#335000
18
1U
17
1Q
1T
1V
1N
1P
1S
1M
1R
0k
1J
0O
0G
1I
1W
0X
0Y
0Z
0[
0\
0L
1@
1l
0;
1F
0H
06
0c
0b
0a
0`
04
0$
19
b100 p
b1010101 &
b1010101 g
b1010101 u
b1010101 o
b0 '
b0 j
b0 t
b10 (
b10 f
b10 m
b10 s
1%
1r
0!
1n
1*
#340000
b10101010 .
b10101010 i
b11 ,
b11 h
0*
#345000
0\
0[
0Z
18
0Y
1U
17
1Q
1T
1V
0X
1N
1P
1S
1M
1R
0k
1J
1K
0O
0G
1I
0W
0L
0E
1;
1F
0H
1B
b11 p
1*
#350000
0-
0*
#355000
1W
0l
0D
0B
b10 p
1*
#360000
0*
#365000
13
1)
0]
0A
09
15
1<
0W
0:
1B
b1 p
1*
#370000
0*
#375000
1\
1[
1Z
08
1Y
0U
07
0Q
0T
0V
0N
0P
0S
1W
1k
1X
0M
0R
1G
1O
0B
0J
1L
05
0I
0<
0F
0K
1l
1H
03
0)
1:
1D
1E
1d
1b
1`
1^
1A
14
1$
02
b1010101 '
b1010101 j
b1010101 t
b0 p
1!
0#
0n
1*
#380000
b1010101 z
0x
b10 w
0*
#385000
0!
1*
#390000
1]
0W
0X
0Y
0Z
0[
0\
12
0@
0k
1C
16
b0 .
b0 i
b10 ,
b10 h
0/
1-
0*
#395000
18
1U
17
1Q
1T
1V
1N
1P
1S
1M
1R
0O
0G
1J
0L
1I
1F
1K
1W
0X
0Y
0Z
0[
0\
0H
1@
0l
0k
0D
0E
06
04
0$
19
b10 p
b0 &
b0 g
b0 u
b0 o
0%
0r
1n
1*
#400000
b0 |
0-
0*
#405000
13
1)
0]
0A
09
15
1<
0W
0:
1B
b1 p
1*
#406000
b1 |
#410000
0*
#415000
1\
1[
1Z
08
1Y
0U
07
0Q
0T
0V
0N
0P
0S
1W
1k
1X
0M
0R
1G
1O
0B
0J
1L
05
0I
0<
0F
0K
1l
1H
03
0)
1:
1D
1E
1A
14
1$
02
b0 p
1!
b1010101 "
b1010101 q
0n
1*
#416000
b0 z
b11 w
b1001 1
b10 |
#420000
1]
0W
0X
0Y
0Z
0[
0\
12
0@
0k
16
b11 ,
b11 h
1-
0*
#425000
18
1U
17
1Q
1T
1V
1N
1P
1S
1M
1R
0O
0G
1J
0L
1I
1W
0X
0Y
0Z
0[
0\
1F
1K
1@
0l
0k
0H
06
0D
0E
04
0$
0d
0b
0`
0^
19
1n
0!
b0 '
b0 j
b0 t
b11 (
b11 f
b11 m
b11 s
b10 p
1*
#430000
b0 |
0-
0*
#435000
13
1)
0]
0A
09
15
1<
0W
0:
1B
b1 p
1*
#436000
b1 |
#440000
0*
#445000
1\
1[
1Z
08
1Y
0U
07
0Q
0T
0V
0N
0P
0S
1W
1k
1X
0M
0R
1G
1O
0B
0J
1L
05
0I
0<
0F
0K
03
0)
1l
1H
1:
1D
1E
1A
14
1$
02
0n
b0 "
b0 q
1!
b0 p
1*
#446000
b1010 1
b10 |
#450000
1]
0W
0X
0Y
0Z
0[
0\
12
0@
0l
0C
16
b1110111 .
b1110111 i
b0 ,
b0 h
1/
1-
0*
#455000
18
1U
17
1Q
1T
1V
1N
1P
1S
1M
1R
0k
1J
0O
0G
1I
1W
0X
0Y
0Z
0[
0\
0L
1@
1l
0;
1F
0H
06
1e
1c
1`
1^
04
0$
19
b100 p
b1110111 &
b1110111 g
b1110111 u
b1110111 o
b10100101 '
b10100101 j
b10100101 t
b0 (
b0 f
b0 m
b0 s
1%
1r
0!
1n
1*
#460000
14
10
0-
0*
#465000
1\
1[
1Z
08
1Y
0U
07
0Q
0T
0V
1X
0N
0P
0S
0M
0R
1k
0J
1O
1G
0I
1L
1;
0F
1H
0]
09
02
0n
0%
0r
b0 &
b0 g
b0 u
b0 o
b0 p
1*
#470000
1$
b10100101 z
b0 w
00
0*
#475000
1*
#480000
1]
0W
0X
0Y
0Z
0[
0\
12
0@
0k
1C
16
b0 .
b0 i
0/
1-
0*
#485000
18
1U
17
1Q
1T
1V
1N
1P
1S
1M
1R
0O
0G
1J
0L
1I
1W
0X
0Y
0Z
0[
0\
1F
1K
1@
0l
0k
0H
06
0D
0E
04
0$
19
1n
b10 p
1*
#490000
b0 |
0-
0*
#495000
13
1)
0]
0A
09
15
1<
0W
0:
1B
b1 p
1*
#496000
b1 |
#500000
0*
#505000
1\
1[
1Z
08
1Y
0U
07
0Q
0T
0V
0N
0P
0S
1W
1k
1X
0M
0R
1G
1O
0B
0J
1L
05
0I
0<
0F
0K
03
0)
1l
1H
1:
1D
1E
1A
14
1$
02
0n
b10100101 "
b10100101 q
1!
b0 p
1*
#506000
b1011 1
b10 |
